README.md
setup.py
Jump_Bike_DC_API_Wrapper.egg-info/PKG-INFO
Jump_Bike_DC_API_Wrapper.egg-info/SOURCES.txt
Jump_Bike_DC_API_Wrapper.egg-info/dependency_links.txt
Jump_Bike_DC_API_Wrapper.egg-info/requires.txt
Jump_Bike_DC_API_Wrapper.egg-info/top_level.txt
src/main.py