Metadata-Version: 1.0
Name: Jump-Bike-DC-API-Wrapper
Version: 0.1
Summary: Python Wrapper for Jump Bike D.C's open API.
Home-page: https://github.com/Leschonander/Jump-Bike-D.C-Python-API-Wrapper
Author: Lars E. Schonander
Author-email: leschonander@gmail.com
License: MIT
Platform: UNKNOWN
